pyhelios3d-0.1.71.dist-info/RECORD
pyhelios3d-0.1.71.dist-info/WHEEL
pyhelios3d-0.1.71.dist-info/entry_points.txt
pyhelios3d-0.1.71.dist-info/top_level.txt
pyhelios3d-0.1.71.dist-info/METADATA
pyhelios3d-0.1.71.dist-info/licenses/LICENSE
pyhelios/PhotosynthesisModel.py
pyhelios/StomatalConductance.py
pyhelios/_types.py
pyhelios/WeberPennTree.py
pyhelios/EnergyBalance.py
pyhelios/_version.py
pyhelios/Global.py
pyhelios/__init__.py
pyhelios/types.py
pyhelios/Logger.py
pyhelios/runtime.py
pyhelios/Context.py
pyhelios/RadiationModel.py
pyhelios/_stub.c
pyhelios/exceptions.py
pyhelios/SolarPosition.py
pyhelios/dev_utils.py
pyhelios/_stub.cpython-311-darwin.so
pyhelios/Visualizer.py
pyhelios/wrappers/UStomatalConductanceWrapper.py
pyhelios/wrappers/UVisualizerWrapper.py
pyhelios/wrappers/UEnergyBalanceWrapper.py
pyhelios/wrappers/URadiationModelWrapper.py
pyhelios/wrappers/__init__.py
pyhelios/wrappers/UContextWrapper.py
pyhelios/wrappers/DataTypes.py
pyhelios/wrappers/ULoggerWrapper.py
pyhelios/wrappers/UWeberPennTreeWrapper.py
pyhelios/wrappers/UPhotosynthesisWrapper.py
pyhelios/wrappers/USolarPositionWrapper.py
pyhelios/wrappers/UGlobalWrapper.py
pyhelios/types/photosynthesis.py
pyhelios/types/__init__.py
pyhelios/config/config_manager.py
pyhelios/config/plugin_metadata.py
pyhelios/config/__init__.py
pyhelios/config/dependency_resolver.py
pyhelios/plugins/libz.dylib
pyhelios/plugins/libGLEW.dylib
pyhelios/plugins/registry.py
pyhelios/plugins/__init__.py
pyhelios/plugins/libGLEW.2.2.dylib
pyhelios/plugins/libz.1.3.1.dylib
pyhelios/plugins/loader.py
pyhelios/plugins/libhelios.dylib
pyhelios/plugins/libz.1.dylib
pyhelios/plugins/__main__.py
pyhelios/plugins/libGLEW.2.2.0.dylib
pyhelios/.dylibs/libxcb.1.dylib
pyhelios/.dylibs/libICE.6.dylib
pyhelios/.dylibs/libX11.6.dylib
pyhelios/.dylibs/libXau.6.dylib
pyhelios/.dylibs/libXext.6.dylib
pyhelios/.dylibs/libSM.6.dylib
pyhelios/assets/__init__.py
pyhelios/assets/__pycache__/__init__.cpython-39.pyc
pyhelios/assets/__pycache__/__init__.cpython-310.pyc
pyhelios/assets/build/plugins/weberpenntree/wood/wood.jpg
pyhelios/assets/build/plugins/weberpenntree/wood/wood2.jpg
